torchluent/__init__.py
torchluent/fluent_module.py
torchluent-0.0.4.dist-info/LICENSE.txt
torchluent-0.0.4.dist-info/METADATA
torchluent-0.0.4.dist-info/WHEEL
torchluent-0.0.4.dist-info/top_level.txt
torchluent-0.0.4.dist-info/RECORD
