Metadata-Version: 2.1
Name: torchluent
Version: 0.0.4
Summary: Build pytorch models in a fluent interface
Home-page: https://github.com/tjstretchalot/torchluent
Author: Timothy Moore
Author-email: mtimothy984@gmail.com
License: CC0
Keywords: torch fluent models machinelearning
Platform: UNKNOWN
Classifier: Programming Language :: Python :: 3
Classifier: Programming Language :: Python :: 3.6
Classifier: Programming Language :: Python :: 3.7
Classifier: License :: CC0 1.0 Universal (CC0 1.0) Public Domain Dedication
Classifier: Topic :: Utilities
Requires-Python: >=3.6
Requires-Dist: torch (>=1.1.0)
Requires-Dist: torchvision (>=0.3.0)
Requires-Dist: numpy
Requires-Dist: pytypeutils
